pyciphering/__init__.py
pyciphering/atbash.py
pyciphering/bifid.py
pyciphering/caesar.py
pyciphering/polybius.py
pyciphering/trifid.py
pyciphering/viegenere.py
pyciphering-0.1.5.dist-info/LICENSE
pyciphering-0.1.5.dist-info/METADATA
pyciphering-0.1.5.dist-info/WHEEL
pyciphering-0.1.5.dist-info/top_level.txt
pyciphering-0.1.5.dist-info/RECORD
