Metadata-Version: 2.1
Name: pyciphering
Version: 0.1.5
Summary: An awesome package to text ciphering
Home-page: https://github.com/majsterkovic/pyciphering
Author: majsterkovic
Author-email: mariusz8h@o2.pl
License: MIT
Keywords: ciphers,encryption,encode,decode
Platform: UNKNOWN
Classifier: Programming Language :: Python :: 3
Classifier: License :: OSI Approved :: MIT License
Classifier: Operating System :: OS Independent
License-File: LICENSE
